CONTRIBUTING.rst
LICENSE
MANIFEST.in
README.rst
setup.cfg
setup.py
AppDynamicsRESTx.egg-info/PKG-INFO
AppDynamicsRESTx.egg-info/SOURCES.txt
AppDynamicsRESTx.egg-info/dependency_links.txt
AppDynamicsRESTx.egg-info/requires.txt
AppDynamicsRESTx.egg-info/top_level.txt
appd/__init__.py
appd/cmdline.py
appd/request.py
appd/time.py
appd/model/__init__.py
appd/model/account.py
appd/model/action_suppressions.py
appd/model/application.py
appd/model/audit_history.py
appd/model/backend.py
appd/model/business_transaction.py
appd/model/config_variable.py
appd/model/entity_def.py
appd/model/event.py
appd/model/hourly_license_usage.py
appd/model/license_module.py
appd/model/license_usage.py
appd/model/metric_data.py
appd/model/metric_treenode.py
appd/model/metric_value.py
appd/model/node.py
appd/model/policy_violation.py
appd/model/set_controller_url.py
appd/model/snapshot.py
appd/model/tier.py
data/backend_metrics.xml
data/bt_list.xml
data/business_transactions.json
data/licenses_by_host.csv
data/licenses_by_host.xlsx
data/metric_tree_0.json
data/metric_tree_1.json
data/metric_tree_2.json
data/nodes.json
data/tiers.json
docs/Makefile
docs/conf.py
docs/contributing.rst
docs/faq.rst
docs/history.rst
docs/index.rst
docs/installation.rst
docs/make.bat
docs/readme.rst
docs/ref.rst
docs/usage.rst
docs/api/cmdline.rst
examples/audit.py
examples/backend_metrics.py
examples/bt_metrics.py
examples/dependencies.py
examples/healthrule_violations.py
examples/license_count.py
examples/license_count_by_app.py
examples/license_count_by_appgroup.py
examples/license_count_by_env.py
examples/license_list_hosts.py
examples/license_report_to_csv.py
examples/nodelist.py
examples/sample.py
examples/usage_chart.py
examples/usage_chart_java.py
examples/xsd/backend_metrics.xsd
examples/xsd/bt_metrics.xsd
templates/audit.jinja.html
test/test.py
test/test_action_suppressions.py
test/test_create_event.py
test/test_create_user.py
test/test_exclude_bts.py
test/test_export_actions.py
test/test_export_analytics_dynamic_service_configs.py
test/test_export_custom_dashboard.py
test/test_export_email_action_templates.py
test/test_export_entry_point_type.py
test/test_export_entry_points.py
