Metadata-Version: 2.1
Name: AppDynamicsRESTx
Version: 0.4.22
Summary: AppDynamics REST API Library
Home-page: https://github.com/homedepot/AppDynamicsRESTx
Author: Todd Radel
Author-email: tradel@appdynamics.com
Maintainer: Mike Phillipson
Maintainer-email: MICHAEL_PHILLIPSON1@homedepot.com
License: Apache
Platform: any
Classifier: Programming Language :: Python
Classifier: Intended Audience :: Developers
Classifier: Development Status :: 4 - Beta
Classifier: Natural Language :: English
Classifier: Operating System :: OS Independent
Classifier: Topic :: System :: Monitoring
Classifier: Topic :: Software Development :: Libraries :: Python Modules
Classifier: Programming Language :: Python :: 2
Classifier: Programming Language :: Python :: 2.6
Classifier: Programming Language :: Python :: 2.7
Classifier: Programming Language :: Python :: 3
Classifier: Programming Language :: Python :: 3.3
Classifier: Programming Language :: Python :: 3.4
Classifier: Programming Language :: Python :: 3.5
Classifier: Programming Language :: Python :: 3.6
Classifier: Programming Language :: Python :: 3.7
Classifier: Programming Language :: Python :: 3.8
Provides-Extra: examples
Provides-Extra: testing
License-File: LICENSE
